odoo/addons/server_env_connector_jira/README.rst
odoo/addons/server_env_connector_jira/__init__.py
odoo/addons/server_env_connector_jira/__manifest__.py
odoo/addons/server_env_connector_jira/i18n/server_env_connector_jira.pot
odoo/addons/server_env_connector_jira/models/__init__.py
odoo/addons/server_env_connector_jira/models/jira_backend.py
odoo/addons/server_env_connector_jira/static/description/icon.png
odoo11_addon_server_env_connector_jira-11.0.1.0.0.99.dev4.dist-info/METADATA
odoo11_addon_server_env_connector_jira-11.0.1.0.0.99.dev4.dist-info/RECORD
odoo11_addon_server_env_connector_jira-11.0.1.0.0.99.dev4.dist-info/WHEEL
odoo11_addon_server_env_connector_jira-11.0.1.0.0.99.dev4.dist-info/top_level.txt
